CHANGES.md
LICENSE
MANIFEST.in
README.md
setup.py
vu/__init__.py
vu/app.py
vu/checkers.py
vu/cmd.py
vu/config.py
vu/handlers.py
vu/helpers.py
vu/main.py
vu/settings.py
vu.egg-info/PKG-INFO
vu.egg-info/SOURCES.txt
vu.egg-info/dependency_links.txt
vu.egg-info/entry_points.txt
vu.egg-info/requires.txt
vu.egg-info/top_level.txt
vu/medias/css/.DS_Store
vu/medias/css/bootstrap.min.css
vu/medias/fonts/glyphicons-halflings-regular.eot
vu/medias/fonts/glyphicons-halflings-regular.svg
vu/medias/fonts/glyphicons-halflings-regular.ttf
vu/medias/fonts/glyphicons-halflings-regular.woff
vu/templates/base.html
vu/templates/index.html
vu/utils/__init__.py
vu/utils/six.py
vu/utils/termcolors.py