Metadata-Version: 1.0
Name: vu
Version: 0.1.1
Summary: Small service that helps you to check the health of your services.
Home-page: https://bitbucket.org/m_clement/vu/
Author: Martyn CLEMENT
Author-email: martyn.clement@gmail.com
License: MIT
Platform: UNKNOWN
Classifier: Development Status :: 4 - Beta
Classifier: Environment :: Web Environment
Classifier: Intended Audience :: Developers
Classifier: Natural Language :: French
Classifier: License :: OSI Approved :: MIT License
Classifier: Operating System :: OS Independent
Classifier: Programming Language :: Python
Classifier: Programming Language :: Python :: 2
Classifier: Programming Language :: Python :: 2.6
Classifier: Programming Language :: Python :: 2.7
Classifier: Topic :: Software Development :: Libraries :: Python Modules
